{
  "meta": {
    "university": "부산외국어대학교",
    "main_phone": "051-509-5000",
    "main_fax": "051-509-5005",
    "updated": "2026-04",
    "note": "내선번호는 051-509-XXXX 형태로 외부에서 연결 가능"
  },
  "admin_offices": [
    {
      "name": "대표전화",
      "aliases": ["대표", "본교", "학교"],
      "extension": "5000",
      "phone": "051-509-5000"
    },
    {
      "name": "경비종합상황실",
      "aliases": ["경비실", "경비", "시설"],
      "extension": "6810",
      "phone": "051-509-6810"
    },
    {
      "name": "교무처",
      "aliases": ["교무", "교무팀"],
      "extension": "6014",
      "phone": "051-509-6014"
    },
    {
      "name": "학사지원팀",
      "aliases": ["학사지원", "학사팀", "수강신청", "성적", "학적", "휴학", "복학"],
      "extension": "5181",
      "phone": "051-509-5181"
    },
    {
      "name": "입학홍보처",
      "aliases": ["입학처", "입학", "입학관리", "입학관리팀"],
      "extension": "5300",
      "phone": "051-509-5300"
    },
    {
      "name": "입학관리팀",
      "aliases": ["입학팀", "입학관리팀"],
      "extension": "5301",
      "phone": "051-509-5301"
    },
    {
      "name": "국제교류처",
      "aliases": ["국제처", "국제교류", "교환학생", "해외연수", "유학"],
      "extension": "5522",
      "phone": "051-509-5522"
    },
    {
      "name": "국제교류팀",
      "aliases": ["국제교류팀", "해외파견"],
      "extension": "5321",
      "phone": "051-509-5321"
    },
    {
      "name": "행정지원처",
      "aliases": ["행정처", "행정지원", "행정"],
      "extension": "5081",
      "phone": "051-509-5081"
    },
    {
      "name": "기획조정처",
      "aliases": ["기획처", "기획조정", "기획"],
      "extension": "5776",
      "phone": "051-509-5776"
    },
    {
      "name": "산학협력단",
      "aliases": ["산학협력", "산학"],
      "extension": "5784",
      "phone": "051-509-5784"
    },
    {
      "name": "중앙도서관",
      "aliases": ["도서관", "학술정보"],
      "extension": "6937",
      "phone": "051-509-6937"
    },
    {
      "name": "학술정보팀",
      "aliases": ["학술정보팀", "도서관 대출"],
      "extension": "6441",
      "phone": "051-509-6441"
    },
    {
      "name": "학생상담센터",
      "aliases": ["상담센터", "심리상담", "학생상담"],
      "extension": "6343",
      "phone": "051-509-6343"
    },
    {
      "name": "장애학생지원센터",
      "aliases": ["장애지원", "장애학생"],
      "extension": "5161",
      "phone": "051-509-5161"
    },
    {
      "name": "진로개발센터",
      "aliases": ["진로센터", "진로상담", "취업", "취업지원"],
      "extension": "6351",
      "phone": "051-509-6351"
    },
    {
      "name": "학생진로처",
      "aliases": ["진로처", "대학일자리", "일자리"],
      "extension": "6153",
      "phone": "051-509-6153"
    },
    {
      "name": "대학원교학팀",
      "aliases": ["대학원", "대학원팀", "대학원 수강"],
      "extension": "5141",
      "phone": "051-509-5141"
    },
    {
      "name": "현장실습지원센터",
      "aliases": ["현장실습", "실습", "현장실습센터"],
      "extension": "5750",
      "phone": "051-509-5750"
    },
    {
      "name": "평생교육/교육연수원",
      "aliases": ["평생교육원", "교육연수원", "평생교육"],
      "extension": "5261",
      "phone": "051-509-5261"
    },
    {
      "name": "한국어문화교육원",
      "aliases": ["한국어교육원", "한국어원", "한국어 과정"],
      "extension": "5940",
      "phone": "051-509-5940"
    },
    {
      "name": "부속의원",
      "aliases": ["의원", "의무실", "병원", "의료"],
      "extension": "5681",
      "phone": "051-509-5681"
    },
    {
      "name": "생활관",
      "aliases": ["기숙사", "생활관", "외성생활관", "기숙사관"],
      "extension": "5407",
      "phone": "051-509-5407"
    },
    {
      "name": "국제학생지원팀",
      "aliases": ["외국인학생", "국제학생", "유학생 지원"],
      "extension": "5294",
      "phone": "051-509-5294"
    },
    {
      "name": "국제학생통합지원센터",
      "aliases": ["국제학생센터", "외국인 유학생"],
      "extension": "5261",
      "phone": "051-509-5261"
    },
    {
      "name": "창업지원단",
      "aliases": ["창업", "창업지원", "스타트업"],
      "extension": "5784",
      "phone": "051-509-5784"
    },
    {
      "name": "대학인권센터",
      "aliases": ["인권센터", "인권"],
      "extension": "6535",
      "phone": "051-509-6535"
    },
    {
      "name": "PC유지관리",
      "aliases": ["PC", "컴퓨터 수리", "IT 지원"],
      "extension": "6990",
      "phone": "051-509-6990"
    }
  ],
  "colleges": [
    {
      "name": "유럽미주대학",
      "aliases": ["유럽미주대", "유럽대학"],
      "departments": [
        {
          "name": "영어학부",
          "aliases": ["영어학부", "영어과", "영어"],
          "type": "학부",
          "extension": "5551",
          "phone": "051-509-5551",
          "office": "D594",
          "sub_units": [
            {
              "name": "영어전공",
              "aliases": ["영어전공"],
              "extension": "5552",
              "phone": "051-509-5552",
              "office": "D594"
            },
            {
              "name": "영어통번역전공",
              "aliases": ["영어통번역", "영어 통역", "영어 번역"],
              "extension": "5551",
              "phone": "051-509-5551",
              "office": "D594"
            }
          ]
        },
        {
          "name": "유럽학부",
          "aliases": ["유럽학부"],
          "type": "학부",
          "extension": "5581",
          "phone": "051-509-5581",
          "sub_units": [
            {
              "name": "프랑스어전공",
              "aliases": ["프랑스어전공", "프랑스어과", "프랑스어", "프랑스"],
              "extension": "5581",
              "phone": "051-509-5581",
              "office": "D595"
            },
            {
              "name": "독일어전공",
              "aliases": ["독일어전공", "독일어과", "독일어", "독일"],
              "extension": "5601",
              "phone": "051-509-5601",
              "office": "D595"
            },
            {
              "name": "스페인어전공",
              "aliases": ["스페인어전공", "스페인어과", "스페인어", "스페인", "서반아어"],
              "extension": "5621",
              "phone": "051-509-5621",
              "office": "D596"
            },
            {
              "name": "포르투갈(브라질)어전공",
              "aliases": ["포르투갈어전공", "포르투갈어", "포르투갈", "브라질어"],
              "extension": "5630",
              "phone": "051-509-5630",
              "office": "D596"
            },
            {
              "name": "이탈리아어전공",
              "aliases": ["이탈리아어전공", "이탈리어전공", "이탈리아어", "이탈리아", "이탈리어"],
              "extension": "5671",
              "phone": "051-509-5671",
              "office": "D595"
            },
            {
              "name": "러시아어전공",
              "aliases": ["러시아어전공", "러시아어과", "러시아어", "러시아"],
              "extension": "5707",
              "phone": "051-509-5707",
              "office": "D562"
            },
            {
              "name": "유럽지역통상전공",
              "aliases": ["유럽지역통상", "유럽통상"],
              "extension": "5681",
              "phone": "051-509-5681",
              "office": "D595"
            }
          ]
        }
      ]
    },
    {
      "name": "아시아대학",
      "aliases": ["아시아대"],
      "departments": [
        {
          "name": "일본어융합학부",
          "aliases": ["일본어학부", "일본어융합학부", "일본어과", "일본어", "일본"],
          "type": "학부",
          "extension": "5711",
          "phone": "051-509-5711",
          "office": "D597",
          "sub_units": [
            {
              "name": "한일문화콘텐츠전공",
              "aliases": ["한일문화콘텐츠", "한일콘텐츠"],
              "extension": "5711",
              "phone": "051-509-5711",
              "office": "D597"
            },
            {
              "name": "비즈니스일본어전공",
              "aliases": ["비즈니스일본어", "비즈일본어"],
              "extension": "5741",
              "phone": "051-509-5741",
              "office": "D597"
            },
            {
              "name": "일본어IT전공",
              "aliases": ["일본어IT", "일본어 IT"],
              "extension": "5741",
              "phone": "051-509-5741",
              "office": "D597"
            }
          ]
        },
        {
          "name": "중국학부",
          "aliases": ["중국학부", "중국어과", "중국어", "중국"],
          "type": "학부",
          "extension": "5771",
          "phone": "051-509-5771",
          "office": "D561",
          "sub_units": [
            {
              "name": "중국어전공",
              "aliases": ["중국어전공"],
              "extension": "5771",
              "phone": "051-509-5771",
              "office": "D561"
            },
            {
              "name": "중국지역통상전공",
              "aliases": ["중국지역통상", "중국통상"],
              "extension": "5799",
              "phone": "051-509-5799",
              "office": "D561"
            }
          ]
        },
        {
          "name": "태국어전공",
          "aliases": ["태국어전공", "태국어과", "태국어", "태국"],
          "type": "전공",
          "extension": "5868",
          "phone": "051-509-5868",
          "office": "D423"
        },
        {
          "name": "인도네시아·말레이시아전공",
          "aliases": ["인도네시아전공", "말레이시아전공", "인도네시아", "말레이시아", "인니어"],
          "type": "전공",
          "extension": "5811",
          "phone": "051-509-5811",
          "office": "D423"
        },
        {
          "name": "베트남어전공",
          "aliases": ["베트남어전공", "베트남어과", "베트남어", "베트남"],
          "type": "전공",
          "extension": "5869",
          "phone": "051-509-5869",
          "office": "D423"
        },
        {
          "name": "미얀마어전공",
          "aliases": ["미얀마어전공", "미얀마어", "미얀마"],
          "type": "전공",
          "extension": "5870",
          "phone": "051-509-5870",
          "office": "D423"
        },
        {
          "name": "인도어전공",
          "aliases": ["인도어전공", "힌디어", "인도어", "인도"],
          "type": "전공",
          "extension": "5891",
          "phone": "051-509-5891",
          "office": "D564"
        },
        {
          "name": "아랍어전공",
          "aliases": ["아랍어전공", "아랍전공", "아랍어", "아랍"],
          "type": "전공",
          "extension": "5881",
          "phone": "051-509-5881",
          "office": "D564"
        },
        {
          "name": "튀르키예어전공",
          "aliases": ["튀르키예어전공", "터키어전공", "터키어", "튀르키예어", "터키"],
          "type": "전공",
          "extension": "5708",
          "phone": "051-509-5708",
          "office": "D562"
        }
      ]
    },
    {
      "name": "사회과학대학",
      "aliases": ["사회과학대", "사회대"],
      "departments": [
        {
          "name": "사회복지전공",
          "aliases": ["사회복지전공", "사회복지학과", "사회복지", "복지"],
          "type": "전공",
          "extension": "6318",
          "phone": "051-509-6318",
          "office": "D502-1"
        },
        {
          "name": "상담심리전공",
          "aliases": ["상담심리전공", "심리상담전공", "상담심리", "심리학"],
          "type": "전공",
          "extension": "6866",
          "phone": "051-509-6866",
          "office": "I416-1"
        },
        {
          "name": "경찰행정전공",
          "aliases": ["경찰행정전공", "경찰행정", "경찰"],
          "type": "전공",
          "extension": "5991",
          "phone": "051-509-5991",
          "office": "D502-1"
        },
        {
          "name": "사이버경찰전공",
          "aliases": ["사이버경찰전공", "사이버경찰"],
          "type": "전공",
          "extension": "6321",
          "phone": "051-509-6321",
          "office": "I416-1"
        },
        {
          "name": "한국어교육전공",
          "aliases": ["한국어교육전공", "한국어교육", "국어교육"],
          "type": "전공",
          "extension": "5931",
          "phone": "051-509-5931",
          "office": "D502-1"
        },
        {
          "name": "외교전공",
          "aliases": ["외교전공", "외교학", "외교"],
          "type": "전공",
          "extension": "6011",
          "phone": "051-509-6011",
          "office": "D502-1"
        },
        {
          "name": "국제개발협력전공",
          "aliases": ["국제개발협력", "개발협력", "ODA"],
          "type": "전공",
          "extension": "6011",
          "phone": "051-509-6011",
          "office": "D502-1"
        },
        {
          "name": "글로벌인재융합전공",
          "aliases": ["글로벌인재융합", "인재융합"],
          "type": "전공",
          "extension": "5791",
          "phone": "051-509-5791",
          "office": "D522"
        },
        {
          "name": "글로벌미래융합학부",
          "aliases": ["글로벌미래융합", "미래융합학부", "미래융합"],
          "type": "학부",
          "extension": "5813",
          "phone": "051-509-5813",
          "office": "B209",
          "sub_units": [
            {
              "name": "스포츠재활전공",
              "aliases": ["스포츠재활", "스포츠"],
              "extension": "6591",
              "phone": "051-509-6591",
              "office": "B204"
            },
            {
              "name": "사회체육전공",
              "aliases": ["사회체육"],
              "extension": "6301",
              "phone": "051-509-6301",
              "office": "B204"
            },
            {
              "name": "시민영어교육학과",
              "aliases": ["시민영어교육", "시민영어"],
              "extension": "5813",
              "phone": "051-509-5813",
              "office": "D565"
            },
            {
              "name": "글로벌문화비즈니스전공",
              "aliases": ["글로벌문화비즈니스", "문화비즈니스"],
              "extension": "6789",
              "phone": "051-509-6789",
              "office": "D566"
            }
          ]
        }
      ]
    },
    {
      "name": "상경대학",
      "aliases": ["상경대", "경상대학"],
      "departments": [
        {
          "name": "경영전공",
          "aliases": ["경영전공", "경영학과", "경영"],
          "type": "전공",
          "extension": "6051",
          "phone": "051-509-6051",
          "office": "D502-1"
        },
        {
          "name": "회계전공",
          "aliases": ["회계전공", "회계학과", "회계"],
          "type": "전공",
          "extension": "6091",
          "phone": "051-509-6091",
          "office": "D502-1"
        },
        {
          "name": "경제금융전공",
          "aliases": ["경제금융전공", "경제전공", "금융전공", "경제", "금융"],
          "type": "전공",
          "extension": "6121",
          "phone": "051-509-6121",
          "office": "I416-1"
        },
        {
          "name": "국제사무전공",
          "aliases": ["국제사무전공", "국제비서사무", "비서사무", "비서"],
          "type": "전공",
          "extension": "6151",
          "phone": "051-509-6151",
          "office": "D502-1"
        },
        {
          "name": "국제마케팅전공",
          "aliases": ["국제마케팅전공", "마케팅전공", "마케팅"],
          "type": "전공",
          "extension": "5947",
          "phone": "051-509-5947",
          "office": "D502-1"
        },
        {
          "name": "국제무역전공",
          "aliases": ["국제무역전공", "무역전공", "무역"],
          "type": "전공",
          "extension": "6071",
          "phone": "051-509-6071",
          "office": "D502-1"
        },
        {
          "name": "국제문화관광전공",
          "aliases": ["국제문화관광", "관광전공", "관광"],
          "type": "전공",
          "extension": "5981",
          "phone": "051-509-5981",
          "office": "D502-1"
        },
        {
          "name": "호텔·컨벤션전공",
          "aliases": ["호텔컨벤션전공", "호텔전공", "호텔", "컨벤션"],
          "type": "전공",
          "extension": "5981",
          "phone": "051-509-5981",
          "office": "D502-1"
        },
        {
          "name": "항공서비스전공",
          "aliases": ["항공서비스전공", "항공서비스", "항공", "스튜어디스"],
          "type": "전공",
          "extension": "6576",
          "phone": "051-509-6576",
          "office": "I416-1"
        },
        {
          "name": "글로벌창업융합전공",
          "aliases": ["글로벌창업융합", "창업융합"],
          "type": "전공",
          "extension": "5597",
          "phone": "051-509-5597"
        }
      ]
    },
    {
      "name": "디지털미디어·IT대학",
      "aliases": ["디지털미디어대학", "IT대학", "디지털대학"],
      "departments": [
        {
          "name": "컴퓨터공학전공",
          "aliases": ["컴퓨터공학전공", "컴퓨터공학", "컴공"],
          "type": "전공",
          "extension": "6221",
          "phone": "051-509-6221",
          "office": "I416-1"
        },
        {
          "name": "소프트웨어전공",
          "aliases": ["소프트웨어전공", "소프트웨어", "SW"],
          "type": "전공",
          "extension": "6241",
          "phone": "051-509-6241",
          "office": "I416-1"
        },
        {
          "name": "스마트융합보안전공",
          "aliases": ["스마트융합보안", "보안전공", "정보보안"],
          "type": "전공",
          "extension": "6247",
          "phone": "051-509-6247",
          "office": "I416-1"
        },
        {
          "name": "전자·인공지능융합전공",
          "aliases": ["전자인공지능융합", "AI융합전공", "전자전공"],
          "type": "전공",
          "extension": "6261",
          "phone": "051-509-6261",
          "office": "I416-1"
        },
        {
          "name": "빅데이터전공",
          "aliases": ["빅데이터전공", "빅데이터"],
          "type": "전공",
          "extension": "6131",
          "phone": "051-509-6131",
          "office": "I416-1"
        },
        {
          "name": "글로벌웹툰콘텐츠전공",
          "aliases": ["웹툰콘텐츠전공", "웹툰전공", "웹툰"],
          "type": "전공",
          "extension": "5452",
          "phone": "051-509-5452",
          "office": "I416-1"
        },
        {
          "name": "영상콘텐츠융합전공",
          "aliases": ["영상콘텐츠", "영상콘텐츠융합"],
          "type": "전공",
          "extension": "5961",
          "phone": "051-509-5961",
          "office": "D502-1"
        },
        {
          "name": "스마트에너지·환경전공",
          "aliases": ["스마트에너지환경", "에너지환경", "환경전공"],
          "type": "전공",
          "extension": "6261",
          "phone": "051-509-6261",
          "office": "I416-1"
        }
      ]
    },
    {
      "name": "글로벌자유전공학부",
      "aliases": ["자유전공학부", "글로벌자유전공", "자유전공"],
      "departments": [
        {
          "name": "글로벌자유전공학부",
          "aliases": ["글로벌자유전공", "자유전공학부", "자유전공"],
          "type": "학부",
          "extension": "6525",
          "phone": "051-509-6525",
          "office": "F102"
        }
      ]
    },
    {
      "name": "만오교양대학",
      "aliases": ["교양대학", "만오교양", "교양학부"],
      "departments": [
        {
          "name": "만오교양대학 교학팀",
          "aliases": ["만오교양대학", "교양대학 사무실", "교양학부 사무실"],
          "type": "행정",
          "extension": "5591",
          "phone": "051-509-5591"
        },
        {
          "name": "융합교양교육센터",
          "aliases": ["융합교양교육", "교양교육센터"],
          "type": "센터",
          "extension": "5787",
          "phone": "051-509-5787"
        }
      ]
    },
    {
      "name": "International College",
      "aliases": ["인터내셔널칼리지", "IC", "국제대학"],
      "departments": [
        {
          "name": "International College",
          "aliases": ["글로벌스터디즈", "Global Studies", "영어코스", "K문화교육", "K문화"],
          "type": "학부",
          "extension": "5791",
          "phone": "051-509-5791",
          "office": "D522"
        }
      ]
    }
  ]
}
